<?xml version="1.0" encoding="utf-8"?>
<rdf:RDF
   xmlns:ns1="https://dbpedia.org/property/"
   xmlns:rdf="http://www.w3.org/1999/02/22-rdf-syntax-ns#"
>
  <rdf:Description rdf:about="http://127.0.0.1:5000/zone/Zona%206%20-%20Sectia%20Biologica/plant/Dianthus%20knappii">
    <ns1:label>Dianthus knappii</ns1:label>
    <ns1:abstract xml:lang="en">Dianthus knappii, or Knapp's carnation, in Bosnian Knapov karanfil or Knapov klinčić, is a perennial herbaceous plant in the carnation family, Caryophyllaceae. It is endemic at Dinaric mountains, on the border area between Herzegovina (Bosnia and Herzegovina) and Montenegro. In chromosome set has 2n = 30.</ns1:abstract>
    <ns1:positioning>---</ns1:positioning>
    <ns1:zone>http://127.0.0.1:5000/zone/Zona%206%20-%20Sectia%20Biologica</ns1:zone>
  </rdf:Description>
</rdf:RDF>
