<?xml version="1.0" encoding="utf-8"?>
<rdf:RDF
   xmlns:ns1="https://dbpedia.org/property/"
   xmlns:rdf="http://www.w3.org/1999/02/22-rdf-syntax-ns#"
>
  <rdf:Description rdf:about="http://127.0.0.1:5000/zone/Zona%204%20-%20Sectia%20Flora%20si%20Vegetatia%20Romaniei/plant/Corylus%20colurna">
    <ns1:label>Corylus colurna</ns1:label>
    <ns1:abstract xml:lang="en">Corylus colurna, the Turkish hazel or Turkish filbert, is a deciduous tree native to southeast Europe and southwest Asia, from the Balkans through northern Turkey to northern Iran. It is also found growing wild in the forests of Western Himalayan range in the north Indian state of Himachal Pradesh particularly in the temperate regions of districts of Kullu, Shimla, Kinnaur district and Chamba district.</ns1:abstract>
    <ns1:positioning>---</ns1:positioning>
    <ns1:zone>Zona 4 - Sectia Flora si Vegetatia Romaniei</ns1:zone>
  </rdf:Description>
</rdf:RDF>
